manim_ext/__init__.py
manim_ext-0.0.1.dist-info/LICENSE
manim_ext-0.0.1.dist-info/METADATA
manim_ext-0.0.1.dist-info/WHEEL
manim_ext-0.0.1.dist-info/top_level.txt
manim_ext-0.0.1.dist-info/RECORD
