Metadata-Version: 2.1
Name: manim-ext
Version: 0.0.1
Summary: A small package containing useful functions and classes for creating manim(ce) animations
Home-page: https://github.com/Roopesh2/manim-ext
Author: Roopes OR
Author-email: roopeshor6@gmail.com
License: UNKNOWN
Platform: UNKNOWN
Classifier: Programming Language :: Python :: 3
Classifier: License :: OSI Approved :: MIT License
Classifier: Operating System :: OS Independent
Requires-Python: >=3.7
